README.md
setup.py
algo_wars.egg-info/PKG-INFO
algo_wars.egg-info/SOURCES.txt
algo_wars.egg-info/dependency_links.txt
algo_wars.egg-info/requires.txt
algo_wars.egg-info/top_level.txt
algowars/__init__.py
algowars/data_visualizer.py
algowars/extractable_historical_data.py
algowars/information.py
algowars/portfolio_dqn_controller.py
algowars/portfolio_optimization.py
algowars/technical_observer.py
algowars/volatility_gan.py
algowars/controllablemodel/__init__.py
algowars/controllablemodel/gancontroller/__init__.py
algowars/controllablemodel/gancontroller/volatility_gan_controller.py
algowars/exception/__init__.py
algowars/exception/stock_history_error.py
algowars/extractablehistoricaldata/__init__.py
algowars/extractablehistoricaldata/extractable_generated_historical_data.py
algowars/extractablehistoricaldata/facade_alpha_vantage.py
algowars/extractablehistoricaldata/facade_yfinance.py
algowars/generativemodel/__init__.py
algowars/generativemodel/recursive_seq2seq_model.py
algowars/generativemodel/recursiveseq2seqmodel/__init__.py
algowars/generativemodel/recursiveseq2seqmodel/multi_fractal_seq2seq_model.py
algowars/noisesampler/__init__.py
algowars/noisesampler/volatility_conditional_noise_sampler.py
algowars/policysampler/__init__.py
algowars/policysampler/portfolio_percent_policy.py
algowars/portfoliooptimization/__init__.py
algowars/portfoliooptimization/sharpe_ratio_maximization.py
algowars/portfoliooptimization/volatility_minimization.py
algowars/technicalobserver/__init__.py
algowars/technicalobserver/bollinger_band_observer.py
algowars/technicalobserver/contrarian_bollinger_band_observer.py
algowars/technicalobserver/contrarian_rsi_observer.py
algowars/technicalobserver/dive_observer.py
algowars/technicalobserver/macd_observer.py
algowars/technicalobserver/multi_trade_observer.py
algowars/technicalobserver/rsi_observer.py
algowars/truesampler/__init__.py
algowars/truesampler/volatility_conditional_true_sampler.py