Metadata-Version: 2.1
Name: algo-wars
Version: 0.0.1
Summary: algo-wars is Python library for Investment Strategies such as Volatility Modeling, Technical Analysis, and Portfolio Optimization. The goal of this library is to provides cues for strategies to investment or trade stock, bond, or cryptocurrency, based on the statistical machine learning and the deep reignforcement learning.
Home-page: https://github.com/accel-brain/accel-brain-code/tree/master/Algorithm-Wars/
Author: accel-brain
Author-email: info@accel-brain.co.jp
License: GPL2
Platform: UNKNOWN
Classifier: Development Status :: 4 - Beta
Classifier: Intended Audience :: Information Technology
Classifier: Intended Audience :: Science/Research
Classifier: Topic :: Scientific/Engineering :: Artificial Intelligence
Classifier: License :: OSI Approved :: GNU General Public License v2 (GPLv2)
Classifier: Programming Language :: Python :: 3
